hence/__init__.py
hence-0.12.1.dist-info/LICENSE
hence-0.12.1.dist-info/METADATA
hence-0.12.1.dist-info/WHEEL
hence-0.12.1.dist-info/RECORD
