Metadata-Version: 2.3
Name: hence
Version: 0.12.1
Summary: Hence, a powerful framework designed to streamline data pipeline, scraping, automation workflow orchestration.
License: AGPL-3.0-or-later
Author: HSN
Author-email: hasanlock@gmail.com
Requires-Python: >=3.11,<3.14
Classifier: Development Status :: 4 - Beta
Classifier: Intended Audience :: Developers
Classifier: License :: OSI Approved :: GNU Affero General Public License v3 or later (AGPLv3+)
Classifier: Operating System :: OS Independent
Classifier: Programming Language :: Python :: 3.11
Classifier: Programming Language :: Python :: 3.12
Classifier: Programming Language :: Python :: 3.13
Classifier: Topic :: Software Development :: Libraries
Classifier: Topic :: Utilities
Requires-Dist: paradag (>=1.2.0,<2.0.0)
Requires-Dist: pydantic (>=2.11,<3.0)
Project-URL: Documentation, https://github.com/0hsn/hence
Project-URL: Homepage, https://github.com/0hsn/hence
Project-URL: Issues, https://github.com/0hsn/hence/issues
Project-URL: Repository, https://github.com/0hsn/hence
